MANIFEST.in
Mayavi.rst
README.rst
links.rst
setup.py
src/fc_mayavi4mesh/__init__.py
src/fc_mayavi4mesh/demos.py
src/fc_mayavi4mesh/simplicial.py
src/fc_mayavi4mesh.egg-info/PKG-INFO
src/fc_mayavi4mesh.egg-info/SOURCES.txt
src/fc_mayavi4mesh.egg-info/dependency_links.txt
src/fc_mayavi4mesh.egg-info/requires.txt
src/fc_mayavi4mesh.egg-info/top_level.txt