Metadata-Version: 2.1
Name: fc-mayavi4mesh
Version: 0.1.2
Summary: The fc_mayavi4mesh package displays simplicial meshes or datas on simplicial meshes by using Mayavi
Home-page: http://www.math.univ-paris13.fr/~cuvelier/software
Author: Francois Cuvelier
Author-email: cuvelier@math.univ-paris13.fr
License: BSD
Platform: Linux
Platform: Mac OS-X
Platform: Windows
Classifier: Topic :: Scientific/Engineering
